datanalyse-0.0.8.dist-info/METADATA
datanalyse-0.0.8.dist-info/WHEEL
datanalyse-0.0.8.dist-info/licenses/LICENSE
datanalyse/__init__.py
datanalyse/dataelement/__init__.py
datanalyse/dataelement/dataelement.py
datanalyse/dataelement/dfmanipulation.py
datanalyse/dataelement/formate.py
datanalyse/dataelement/stoffwerte.py
datanalyse/diagramme/__init__.py
datanalyse/diagramme/balken.py
datanalyse/diagramme/diagramm.py
datanalyse/diagramme/globalbewertung.py
datanalyse/diagramme/matplotlib_parameter.py
datanalyse/diagramme/zeitreihe.py
datanalyse/pfade.py
datanalyse-0.0.8.dist-info/RECORD
