Metadata-Version: 2.1
Name: datanalyse
Version: 0.0.8
Summary: A data analysis package.
Author-Email: Maximilian Beyer <maximilian.beyer@tu-dresden.de>
Classifier: Programming Language :: Python :: 3
Classifier: License :: OSI Approved :: MIT License
Classifier: Operating System :: OS Independent
Project-URL: Homepage, https://github.com/MakusuB/datanalyse
Project-URL: Bug tracker, https://github.com/MakusuB/datanalyse/issues
Requires-Python: >=3.11
Requires-Dist: pandas>=2.0.1
Requires-Dist: matplotlib>=3.7.1
Requires-Dist: openpyxl>=3.1.2
